aws_eventbridge_explorer-1.0.4.dist-info/licenses/LICENSE
eventbridge/__init__.py
eventbridge/cli.py
eventbridge/core.py
eventbridge/web_server.py
eventbridge/static/custom.css
eventbridge/static/log-observer.js
eventbridge/static/log-viewer.js
eventbridge/static/main.js
eventbridge/static/placeholder.txt
eventbridge/static/icons/event-bus.svg
eventbridge/static/icons/lambda.svg
eventbridge/static/icons/rule.svg
eventbridge/static/icons/sns.svg
eventbridge/static/icons/sqs.svg
eventbridge/templates/index.html
aws_eventbridge_explorer-1.0.4.dist-info/METADATA
aws_eventbridge_explorer-1.0.4.dist-info/WHEEL
aws_eventbridge_explorer-1.0.4.dist-info/entry_points.txt
aws_eventbridge_explorer-1.0.4.dist-info/top_level.txt
aws_eventbridge_explorer-1.0.4.dist-info/RECORD
