Metadata-Version: 2.4
Name: aws-eventbridge-explorer
Version: 1.0.4
Summary: Where Events Meet Clarity - Interactive exploration tool for AWS EventBridge event buses, rules, and targets
Author-email: Sergio Romano <sergio.h.romano@gmail.com>
License: MIT
Project-URL: Homepage, https://github.com/glyphtek/aws-eventbridge-explorer
Project-URL: Bug Tracker, https://github.com/glyphtek/aws-eventbridge-explorer/issues
Classifier: Development Status :: 4 - Beta
Classifier: Intended Audience :: Developers
Classifier: Intended Audience :: System Administrators
Classifier: Programming Language :: Python :: 3
Classifier: Programming Language :: Python :: 3.8
Classifier: Programming Language :: Python :: 3.9
Classifier: Programming Language :: Python :: 3.10
Classifier: Programming Language :: Python :: 3.11
Classifier: License :: OSI Approved :: MIT License
Classifier: Operating System :: OS Independent
Classifier: Topic :: Scientific/Engineering :: Visualization
Classifier: Topic :: System :: Systems Administration
Requires-Python: >=3.8
License-File: LICENSE
Requires-Dist: boto3>=1.28.0
Requires-Dist: networkx>=3.1
Requires-Dist: flask>=2.3.0
Requires-Dist: flask-cors>=4.0.0
Requires-Dist: pygments>=2.15.0
Provides-Extra: dev
Requires-Dist: pytest>=7.0.0; extra == "dev"
Requires-Dist: black>=22.0.0; extra == "dev"
Requires-Dist: isort>=5.10.0; extra == "dev"
Requires-Dist: flake8>=4.0.0; extra == "dev"
Dynamic: license-file
